tiutools/__init__.py
tiutools/__init__.pyi
tiutools/scrape_factory.py
tiutools/scrape_factory.pyi
tiutools/tiutools.py
tiutools/tiutools.pyi
tiutools-0.4.1.dist-info/METADATA
tiutools-0.4.1.dist-info/WHEEL
tiutools-0.4.1.dist-info/RECORD
