Metadata-Version: 2.4
Name: tiutools
Version: 0.4.1
Summary: Collection of functions and classes to interact with TiU infrastructure
Requires-Python: <4.0,>=3.9
Requires-Dist: attrs>=24.3.0
Requires-Dist: keyring>=25.6.0
Requires-Dist: ldap3>=2.9.1
Requires-Dist: pillow>=11.1.0
Requires-Dist: python-dateutil>=2.9.0.post0
Requires-Dist: requests>=2.32.3
Requires-Dist: rich>=13.9.4
Requires-Dist: selenium>=4.27.1
